MANIFEST.in
README.rst
requirements.txt
setup.py
bgvep/__init__.py
bgvep/cli.py
bgvep/globals.py
bgvep/maps.py
bgvep/readers.py
bgvep.egg-info/PKG-INFO
bgvep.egg-info/SOURCES.txt
bgvep.egg-info/dependency_links.txt
bgvep.egg-info/entry_points.txt
bgvep.egg-info/requires.txt
bgvep.egg-info/top_level.txt