Metadata-Version: 2.1
Name: bgvep
Version: 0.1
Summary: BBGLab tool
Home-page: UNKNOWN
Author: Barcelona Biomedical Genomics Lab
Author-email: bbglab@irbbarcelona.org
License: Apache Software License 2.0
Platform: UNKNOWN
